README.txt
setup.cfg
setup.py
docs/CHANGES.txt
docs/HISTORY.txt
docs/LICENSE.GPL
docs/LICENSE.txt
p4a/__init__.py
p4a.plonevideoembed.egg-info/PKG-INFO
p4a.plonevideoembed.egg-info/SOURCES.txt
p4a.plonevideoembed.egg-info/dependency_links.txt
p4a.plonevideoembed.egg-info/entry_points.txt
p4a.plonevideoembed.egg-info/namespace_packages.txt
p4a.plonevideoembed.egg-info/not-zip-safe
p4a.plonevideoembed.egg-info/requires.txt
p4a.plonevideoembed.egg-info/top_level.txt
p4a/plonevideoembed/__init__.py
p4a/plonevideoembed/atct.py
p4a/plonevideoembed/browser.py
p4a/plonevideoembed/configure.zcml
p4a/plonevideoembed/content.py
p4a/plonevideoembed/interfaces.py
p4a/plonevideoembed/media.py
p4a/plonevideoembed/plonevideoembed.txt
p4a/plonevideoembed/sitesetup.py
p4a/plonevideoembed/sitesetup.txt
p4a/plonevideoembed/subtype.py
p4a/plonevideoembed/syndication.py
p4a/plonevideoembed/syndication.zcml
p4a/plonevideoembed/tests.py
p4a/plonevideoembed/video-link.pt
p4a/plonevideoembed/Extensions/install.py
p4a/plonevideoembed/metadata/README.txt
p4a/plonevideoembed/metadata/__init__.py
p4a/plonevideoembed/metadata/configure.zcml
p4a/plonevideoembed/metadata/interfaces.py
p4a/plonevideoembed/metadata/providers.py
p4a/plonevideoembed/metadata/providers.txt
p4a/plonevideoembed/metadata/providers.zcml
p4a/plonevideoembed/metadata/testing.py
p4a/plonevideoembed/metadata/tests.py
p4a/plonevideoembed/metadata/tests.zcml
p4a/plonevideoembed/metadata/youtube-dl