Metadata-Version: 1.0
Name: p4a.plonevideoembed
Version: 1.3
Summary: Plone4Artists video embedding add-on for Plone
Home-page: http://plone.org/products/plone4artistsvideo
Author: Rocky Burt
Author-email: rocky@serverzen.com
License: GPL
Keywords: video youtube Plone4Artists
Platform: UNKNOWN
Classifier: Framework :: Zope2
Classifier: Framework :: Zope3
Classifier: Framework :: Plone
Classifier: Programming Language :: Python
Classifier: Topic :: Software Development :: Libraries :: Python Modules
Classifier: Topic :: Multimedia :: Video
